<window-menu-bar>
    <menu id="file" text="ملف">
        <o id="new_file">ملف جديد</o>
        <o id="new_window">نافذة جديدة</o>
        <o id="new_from_template">جديد من القالب</o>

        <sep/>
        <o id="open_file">فتح...</o>
        <o id="open_recent">فتح الحديث</o>

        <sep/>
        <o id="close_current">إغلاق</o>
        <o id="close_all">إغلاق الكل</o>

        <sep/>
        <o id="save">حفظ</o>
        <o id="save_as">حفظ باسم...</o>
        <o id="save_all">حفظ الكل</o>

        <sep/>
        <o id="browse_all_versions">استعراض كل الإصدارات...</o>

        <sep/>
        <o id="print_dialog">طباعة...</o>
        <o id="page_setup">إعداد الصفحة...</o>
        <o id="print_preview">معاينة الطباعة</o>

        <sep/>
        <o id="import">استيراد...</o>
        <o id="export">تصدير...</o>
        <o id="export_as">تصدير باسم...</o>

        <sep/>
        <o id="quit">إنهاء</o>
    </menu>
    <menu id="edit" text="تحرير">
        <o id="undo">تراجع</o>
        <o id="redo">إعادة</o>
        <o id="cut">قص</o>
        <o id="copy">نسخ</o>
        <o id="paste">لصق</o>
        <o id="paste_special">لصق خاص...</o>
        <o id="delete">حذف</o>
        <o id="select_all">تحديد الكل</o>
        <o id="deselect">إلغاء التحديد</o>
        
        <sep/>
        <o id="find">بحث...</o>
        <o id="find_next">البحث عن التالي</o>
        <o id="find_previous">البحث عن السابق</o>
        <o id="replace">استبدال</o>
        
        <sep/>
        <o id="check_document">التدقيق في المستند</o>
        <o id="check_while_typing">التدقيق الإملائي أثناء الكتابة</o>
    </menu>
    <menu id="view" text="عرض">
        <o id="zoom_in">تكبير</o>
        <o id="zoom_out">تصغير</o>
        <o id="actual_size">الحجم الفعلي</o>
        <o id="fit_to_window">احتواء على النافذة</o>
        <o id="full_screen">ملء الشاشة</o>
        
        <sep/>
        <submenu id="show_windows" text="إظهار النوافذ">
            <o id="toolbar">شريط الأدوات</o>
            <o id="sidebar">الشريط الجانبي</o>
            <o id="rulers">المساطر</o>
            <o id="grid">الشبكة</o>
            <o id="status_bar">شريط الحالة</o>
        </submenu>

        <sep/>
        <o id="single_pane">جزء واحد</o>
        <o id="two_panes">جزأين</o>
        <o id="three_panes">ثلاثة أجزاء</o>

        <sep/>
        <o id="sort_by_name">فرز حسب الاسم</o>
        <o id="sort_by_data_modified">فرز حسب تاريخ التعديل</o>
        <o id="sort_by_size">فرز حسب الحجم</o>
    </menu>
    <menu id="window" text="نافذة">
        <o id="minimize">تصغير</o>
        <o id="zoom_maximize">تكبير/توسيع</o>
        <o id="bring_all_to_front">إحضار الكل إلى الأمام</o>
        <o id="arrange">ترتيب</o>
    </menu>
    <menu id="settings" text="الإعدادات">
        <o id="preferences">التفضيلات...</o>
        <submenu id="themes" text="السمات">
            <o id="modern_dark_theme">مظلم حديث</o>
            <o id="bootstrap_theme">بوتستراب</o>
        </submenu>
        <submenu id="languages" text="اللغات">
            <o id="es_language">الإسبانية</o>
            <o id="en_language">الإنجليزية</o>
        </submenu>
    </menu>
    <menu id="help" text="مساعدة">
        <submenu id="help_options" text="خيارات المساعدة">
            <o id="help_docs">مساعدة</o>
            <o id="keyboard_shortcuts">اختصارات لوحة المفاتيح</o>
            <o id="tutorials">دروس تعليمية</o>

            <sep/>
            <o id="support">دعم</o>
            <o id="licence">ترخيص</o>
        </submenu>

        <sep/>
        <o id="version">إصدار</o>
        <o id="web_page">صفحة الويب</o>
        <o id="check_for_updates">التحقق من وجود تحديثات</o>
        <o id="about_app">حول التطبيق</o>
    </menu>
</window-menu-bar>